kedro_accelerator/plugins/__init__.py
kedro_accelerator-0.3.0.dist-info/METADATA
kedro_accelerator-0.3.0.dist-info/WHEEL
kedro_accelerator-0.3.0.dist-info/entry_points.txt
kedro_accelerator-0.3.0.dist-info/top_level.txt
kedro_accelerator-0.3.0.dist-info/RECORD
