Metadata-Version: 2.1
Name: kedro-accelerator
Version: 0.3.0
Summary: Kedro-Accelerator speeds up pipelines by parallelizing I/O in the background.
Home-page: https://github.com/deepyaman/kedro-accelerator
Author: Deepyaman Datta
Author-email: deepyaman.datta@utexas.edu
License: MIT
Keywords: kedro
Platform: UNKNOWN
Classifier: Development Status :: 3 - Alpha
Classifier: Framework :: Kedro
Classifier: Intended Audience :: Developers
Classifier: License :: OSI Approved :: MIT License
Classifier: Operating System :: OS Independent
Classifier: Programming Language :: Python :: 3 :: Only
Classifier: Programming Language :: Python :: 3.6
Classifier: Programming Language :: Python :: 3.7
Classifier: Programming Language :: Python :: 3.8
Classifier: Topic :: Scientific/Engineering :: Artificial Intelligence
Classifier: Topic :: Software Development :: Libraries :: Python Modules
Requires-Python: >=3.6, <3.9
Requires-Dist: kedro (<0.18,>=0.16)
Provides-Extra: docs
Requires-Dist: sphinx (<2.0,>=1.6.3) ; extra == 'docs'
Requires-Dist: sphinx-rtd-theme (==0.4.1) ; extra == 'docs'
Requires-Dist: nbsphinx (==0.3.4) ; extra == 'docs'
Requires-Dist: nbstripout (==0.3.3) ; extra == 'docs'
Requires-Dist: recommonmark (==0.5.0) ; extra == 'docs'
Requires-Dist: sphinx-autodoc-typehints (==1.6.0) ; extra == 'docs'
Requires-Dist: sphinx-copybutton (==0.2.5) ; extra == 'docs'
Requires-Dist: jupyter-client (<6.0,>=5.1.0) ; extra == 'docs'
Requires-Dist: tornado (<6.0,>=4.2) ; extra == 'docs'
Requires-Dist: ipykernel (<5.0,>=4.8.1) ; extra == 'docs'
